supplier/__init__.py
supplier-0.0.1.dist-info/METADATA
supplier-0.0.1.dist-info/WHEEL
supplier-0.0.1.dist-info/top_level.txt
supplier-0.0.1.dist-info/RECORD
