Metadata-Version: 2.1
Name: supplier
Version: 0.0.1
Summary: Simple library for passing values deeply
Home-page: https://github.com/evinism/supplier
Author: Evin Sellin
Author-email: evinism@gmail.com
License: UNKNOWN
Platform: UNKNOWN
Classifier: Programming Language :: Python :: 3
Classifier: License :: OSI Approved :: MIT License
Classifier: Operating System :: OS Independent
Requires-Python: >=3.6
Requires-Dist: contextvars ; python_version < "3.7"
